where_to/__init__.py
where_to/application.py
where_to/cli.py
where_to/image.py
where_to/lock_screen.py
where_to/outlook.py
where_to/release_notes.md
where_to/windows.py
where_to-0.5.0.dist-info/entry_points.txt
where_to-0.5.0.dist-info/LICENSE
where_to-0.5.0.dist-info/WHEEL
where_to-0.5.0.dist-info/METADATA
where_to-0.5.0.dist-info/RECORD
