Metadata-Version: 2.1
Name: where-to
Version: 0.5.0
Summary: Show upcoming Outlook meetings on the Windows lock screen
Home-page: https://github.com/blairconrad/where-to.git
License: MIT
Author: Blair Conrad
Author-email: blair@blairconrad.com
Requires-Python: >=3.7,<4.0
Classifier: License :: OSI Approved :: MIT License
Classifier: Programming Language :: Python :: 3
Classifier: Programming Language :: Python :: 3.7
Classifier: Programming Language :: Python :: 3.8
Requires-Dist: PILLOW (>=7.0.0,<8.0.0)
Requires-Dist: pywin32 (>=227,<228)
Project-URL: Repository, https://github.com/blairconrad/where-to.git
